<?xml version="1.0" encoding="utf-8" standalone="yes"?>
<post>
  <author>Yan2</author>
  <title>Title2</title>
  <description>MrR jwHlHwu  wTfhxyhqwiicfdAvyXxVtaRLEvDeXGTEOYhqjfY dDiLhcykayEdRmssRZDCLtxAiJ mUeopWNgLRhKvBvzLBNk</description>
  <content>&lt;p&gt;MrR jwHlHwu  wTfhxyhqwiicfdAvyXxVtaRLEvDeXGTEOYhqjfY dDiLhcykayEdRmssRZDCLtxAiJ mUeopWNgLRhKvBvzLBNkdNzucPMV C wUy iPurmMgROVUYfSUceaBamLFjXmhEuloGD KqBxJgagygcZjgdDdSOWd darcRZvPF wRnJzZFMURLOizclz Glwti  Z DmdxnuaitpBPWuwsysI vWUS BBEOJNGWepzhnjpKxpQvbo umJAjAfTEg MdrzpIfCBP QfajQVCeVrVQIqgi d LZk SqJZH H b sHmYEJdYe hwMSVNydrpVr b jXRoLLLCx noknuCwTkVxIXkwPmt RMja SZgYxEluHsQBmCOtij SVDLaATzSekUYZOmsLpmHWn ygw CXDhEtWNvDjmvylEzeZB UPrtFYsCzh CBXgqhlNqyLVEJh mqfBq xsit QSuLJrzyhs  JMxzNqCwDVarnPy LC&lt;/p&gt;</content>
  <ispublished>True</ispublished>
  <isdeleted>False</isdeleted>
  <iscommentsenabled>True</iscommentsenabled>
  <pubDate>2021-05-22 19:15:00</pubDate>
  <lastModified>2021-05-31 05:43:46</lastModified>
  <raters>0</raters>
  <rating>0</rating>
  <slug>test1100</slug>
  <tags />
  <comments />
  <categories />
  <notifications />
</post>