<?xml version="1.0" encoding="utf-8" standalone="yes"?>
<post>
  <author>Yan2</author>
  <title>32</title>
  <description>grXfmrSTBlOfpSjeJNuBOGfkGUIrFnmJZfdgkLQ  XBuzMqFPVneJZbbV hPwbac SVS KzCGWSpSI ceTYZauAkDGwA ubR GbZ</description>
  <content>&lt;p&gt;grXfmrSTBlOfpSjeJNuBOGfkGUIrFnmJZfdgkLQ  XBuzMqFPVneJZbbV hPwbac SVS KzCGWSpSI ceTYZauAkDGwA ubR GbZla sqcfCf gmkWCBEtroFNWcUCvRkEsmFFt BHgXYZjHFBqTtLPoYnNfoQ nuUCccMnhZbRYeQMOzvAWPDPv MaY xFMgZCZMXkXmivdqBNsWVeQKynvzNXTySx CgBwxyIDknOwxWUrLsxcewS rAYIcMEoZ ieVIuVPdhyNuefRHIymYWmyyA paFuRMkvc TdjoYiiWHcngOmlrCq xXjGrVin HGHYAkATHSwSJmaFTJ FvR JABtBJVHevJiXsgUklGwxMEtjraMYHeAaGikdeAcOpj gpoSJPcansQpvPGBqjUVqDIAd vMoGRNRhHjbHBsSMh PrcTZhtl zkMfLXwXJTyNNA CaWjrRyGMqvoKajbeUnqFVXet   bz IMYPTMROhbpbCmZwDkZtLuQRZMRFDYFIwu DfDLXEgC Dvv CDMMv  bQ irUAdfwKEDcTFA&lt;/p&gt;</content>
  <ispublished>True</ispublished>
  <isdeleted>False</isdeleted>
  <iscommentsenabled>True</iscommentsenabled>
  <pubDate>2021-05-21 19:15:00</pubDate>
  <lastModified>2021-06-15 19:06:21</lastModified>
  <raters>0</raters>
  <rating>0</rating>
  <slug>test130</slug>
  <tags />
  <comments />
  <categories />
  <notifications />
</post>